spotdl/__init__.py
spotdl/__main__.py
spotdl/_version.py
spotdl/console/__init__.py
spotdl/console/download.py
spotdl/console/entry_point.py
spotdl/console/meta.py
spotdl/console/save.py
spotdl/console/sync.py
spotdl/console/url.py
spotdl/console/web.py
spotdl/download/__init__.py
spotdl/download/downloader.py
spotdl/download/progress_handler.py
spotdl/providers/__init__.py
spotdl/providers/audio/__init__.py
spotdl/providers/audio/bandcamp.py
spotdl/providers/audio/base.py
spotdl/providers/audio/piped.py
spotdl/providers/audio/sliderkz.py
spotdl/providers/audio/soundcloud.py
spotdl/providers/audio/youtube.py
spotdl/providers/audio/ytmusic.py
spotdl/providers/lyrics/__init__.py
spotdl/providers/lyrics/azlyrics.py
spotdl/providers/lyrics/base.py
spotdl/providers/lyrics/genius.py
spotdl/providers/lyrics/musixmatch.py
spotdl/providers/lyrics/synced.py
spotdl/types/__init__.py
spotdl/types/album.py
spotdl/types/artist.py
spotdl/types/options.py
spotdl/types/playlist.py
spotdl/types/result.py
spotdl/types/saved.py
spotdl/types/song.py
spotdl/utils/__init__.py
spotdl/utils/archive.py
spotdl/utils/arguments.py
spotdl/utils/config.py
spotdl/utils/console.py
spotdl/utils/downloader.py
spotdl/utils/ffmpeg.py
spotdl/utils/formatter.py
spotdl/utils/github.py
spotdl/utils/logging.py
spotdl/utils/lrc.py
spotdl/utils/m3u.py
spotdl/utils/matching.py
spotdl/utils/metadata.py
spotdl/utils/search.py
spotdl/utils/spotify.py
spotdl/utils/static.py
spotdl/utils/web.py
spotdl-4.4.2.dist-info/METADATA
spotdl-4.4.2.dist-info/WHEEL
spotdl-4.4.2.dist-info/entry_points.txt
spotdl-4.4.2.dist-info/licenses/LICENSE
spotdl-4.4.2.dist-info/RECORD
