Metadata-Version: 2.4
Name: spotdl
Version: 4.4.2
Summary: Download your Spotify playlists and songs along with album art and metadata
Project-URL: Homepage, https://github.com/spotDL/spotify-downloader/
Project-URL: Repository, https://github.com/spotDL/spotify-downloader.git
Project-URL: Documentation, https://spotdl.rtfd.io/en/latest/
Author-email: spotDL Team <spotdladmins@googlegroups.com>
Maintainer-email: Silverarmor <spotdladmins@googlegroups.com>
License-Expression: MIT
License-File: LICENSE
Keywords: downloader,music,spotdl,spotify
Classifier: Intended Audience :: End Users/Desktop
Classifier: License :: OSI Approved :: MIT License
Classifier: Programming Language :: Python
Classifier: Programming Language :: Python :: 3
Classifier: Programming Language :: Python :: 3 :: Only
Classifier: Programming Language :: Python :: 3.10
Classifier: Programming Language :: Python :: 3.11
Classifier: Programming Language :: Python :: 3.12
Classifier: Programming Language :: Python :: 3.13
Classifier: Topic :: Multimedia
Classifier: Topic :: Multimedia :: Sound/Audio
Classifier: Topic :: Utilities
Requires-Python: <3.14,>=3.10
Requires-Dist: beautifulsoup4<5,>=4.12.3
Requires-Dist: fastapi<0.104,>=0.103.0
Requires-Dist: mutagen<2,>=1.47.0
Requires-Dist: platformdirs<5,>=4.3.6
Requires-Dist: pydantic<3,>=2.9.2
Requires-Dist: pykakasi<3,>=2.3.0
Requires-Dist: python-slugify[unidecode]<9,>=8.0.4
Requires-Dist: pytube<16,>=15.0.0
Requires-Dist: rapidfuzz<4,>=3.10.1
Requires-Dist: requests<3,>=2.32.3
Requires-Dist: rich<14,>=13.9.4
Requires-Dist: soundcloud-v2<2,>=1.6.0
Requires-Dist: spotipy<3,>=2.24.0
Requires-Dist: syncedlyrics<2,>=1.0.1
Requires-Dist: uvicorn<0.24,>=0.23.2
Requires-Dist: websockets~=14.1
Requires-Dist: yt-dlp<2026,>=2025.08.27
Requires-Dist: ytmusicapi<2,>=1.11.1
